<openerp>
    <data>
        <!-- Inherit quotation report (from module sale) -->
        <template id="report_delivery_inherit_inso" inherit_id="stock.report_delivery_document">
	    <!-- Finds the first table with as class table table-condensed and gives the ability to modify it
		 This will replace everything withing tr (including tr)-->
	    <xpath expr="(//p)[position()=last()]" position="after">
                    <tr style="background-color:lightgray;">
                        <th>Description</th>
                        <th class="text-right">Price</th>
                    </tr>
	    </xpath>
        </template>
    </data>
</openerp>
